nsense_face_cpu/__init__.py
nsense_face_cpu/face/__init__.py
nsense_face_cpu/face/common.py
nsense_face_cpu/model/__init__.py
nsense_face_cpu/model/load_arcface.py
nsense_face_cpu/model/load_onnx.py
nsense_face_cpu/model/load_vino.py
nsense_face_cpu-0.0.13.dist-info/METADATA
nsense_face_cpu-0.0.13.dist-info/WHEEL
nsense_face_cpu-0.0.13.dist-info/top_level.txt
nsense_face_cpu-0.0.13.dist-info/RECORD
